pyckax/__init__.py
pyckax/page.py
pyckax/work.py
pyckax-0.2.0.dist-info/METADATA
pyckax-0.2.0.dist-info/WHEEL
pyckax-0.2.0.dist-info/license
pyckax-0.2.0.dist-info/top_level.txt
pyckax-0.2.0.dist-info/RECORD
