Metadata-Version: 2.1
Name: pyckax
Version: 0.2.0
Summary: yet a crawl library.
Home-page: https://github.com/chaosannals
Author: chaosannals
Author-email: chaosannals@outlook.com
License: MIT
Platform: UNKNOWN
Requires-Dist: beautifulsoup4
